{"data":[{"codparticipant":29714265,"codgroup":44760295,"nom_jugador":"PABLO","any":2009,"codacta":3020761,"codequip":18483072,"dorsal":13,"titular":0,"porter":1,"codequip_local":18483072,"equip_local":"FUNDACIÓ ESPORTIVA GRAMA A","escut_local":"00100_0000574709_fgrama_200x200.png","colorequipacio1_local":"#0000FF","codequip_visitant":40394,"equip_visitant":"SANTS, U.E. A","escut_visitant":"00100_0000671592_uesants_200x200.png","colorequipacio1_visitant":"#FFFFFF","jornada":19,"gols_local":0,"gols_visitant":3}],"dataGols":[],"codparticipant":"29714265","codequip":18483072,"codgroup":44760295,"menuFollowTeams":[{"label":"Infantil B","href":"/classificacio?id=44760295"}]}